README.md
setup.py
zmq_cache/__init__.py
zmq_cache/zmq_cache_server.py
zmq_cache/zmq_message.py
zmq_cache/zmq_message_types.py
zmq_cache/zmq_server.py
zmq_cache.egg-info/PKG-INFO
zmq_cache.egg-info/SOURCES.txt
zmq_cache.egg-info/dependency_links.txt
zmq_cache.egg-info/requires.txt
zmq_cache.egg-info/top_level.txt