Metadata-Version: 2.1
Name: zmq-cache
Version: 0.0.1
Summary: Look aside cache implementation based on ZeroMQ
Home-page: https://github.com/yunluyl/zmq_cache
Author: Yun Lu
Author-email: luyun198993@gmail.com
License: UNKNOWN
Platform: UNKNOWN
Classifier: Programming Language :: Python :: 3
Classifier: License :: OSI Approved :: MIT License
Classifier: Operating System :: OS Independent
